authava_fastapi/__init__.py
authava_fastapi/client.py
authava_fastapi/middleware.py
authava_fastapi-0.1.0.dist-info/METADATA
authava_fastapi-0.1.0.dist-info/WHEEL
authava_fastapi-0.1.0.dist-info/RECORD
