Metadata-Version: 2.3
Name: authava-fastapi
Version: 0.1.0
Summary: FastAPI integration for Authava authentication service
License: MIT
Keywords: fastapi,authentication,authava,oauth,security
Author: Authava
Author-email: support@authava.com
Requires-Python: >=3.8,<4.0
Classifier: Development Status :: 4 - Beta
Classifier: Framework :: FastAPI
Classifier: Intended Audience :: Developers
Classifier: License :: OSI Approved :: MIT License
Classifier: Operating System :: OS Independent
Classifier: Programming Language :: Python :: 3
Classifier: Programming Language :: Python :: 3.8
Classifier: Programming Language :: Python :: 3.9
Classifier: Programming Language :: Python :: 3.10
Classifier: Programming Language :: Python :: 3.11
Classifier: Programming Language :: Python :: 3.12
Classifier: Programming Language :: Python :: 3.13
Classifier: Topic :: Internet :: WWW/HTTP :: Session
Classifier: Topic :: Security
Requires-Dist: cachetools (>=5.3.0,<6.0.0)
Requires-Dist: fastapi (>=0.109.0,<0.110.0)
Requires-Dist: httpx (>=0.26.0,<0.27.0)
Requires-Dist: pydantic (>=2.0.0,<3.0.0)
Requires-Dist: python-jose[cryptography] (>=3.3.0,<4.0.0)
Project-URL: Documentation, https://docs.authava.com/fastapi
Project-URL: Homepage, https://github.com/authava/fastapi
Project-URL: Repository, https://github.com/authava/fastapi
